[
    {
        "categoria": "funcao",
        "tipo": "inteiro",
        "lexema": "principal",
        "parametros": [],
        "retorno": [
            {
                "tipo": "numero",
                "elemento": "0"
            }
        ]
    },
    {
        "tipo": "inteiro",
        "escopo": "global",
        "info": [
            {
                "lexema": "a",
                "categoria": "variavel"
            }
        ]
    },
    {
        "tipo": "inteiro",
        "escopo": "local",
        "info": [
            {
                "lexema": "b",
                "categoria": "variavel"
            }
        ]
    }
]